dsQtCommon/__init__.py
dsQtCommon/api/__init__.py
dsQtCommon/api/common/__init__.py
dsQtCommon/api/stock/__init__.py
dsQtCommon/api/stock/bao_stock.py
dsQtCommon/api/vcoin/__init__.py
dsQtCommon/fields/__init__.py
dsQtCommon/fields/common/__init__.py
dsQtCommon/fields/common/fields.py
dsQtCommon/fields/stock/__init__.py
dsQtCommon/fields/stock/fields.py
dsQtCommon/fields/vcoin/__init__.py
dsQtCommon/indicator/__init__.py
dsQtCommon/indicator/column.py
dsQtCommon/indicator/indicator.py
dsQtCommon/models/__init__.py
dsQtCommon/models/common/__init__.py
dsQtCommon/models/stock/__init__.py
dsQtCommon/models/stock/_bar_base.py
dsQtCommon/models/stock/bar_base.py
dsQtCommon/models/stock/bar_day.py
dsQtCommon/models/stock/meta.py
dsQtCommon/models/stock/stock_meta.py
dsQtCommon/models/vcoin/__init__.py
dsQtCommon/service/__init__.py
dsQtCommon/service/common/__init__.py
dsQtCommon/service/stock/__init__.py
dsQtCommon/service/stock/svr_bar.py
dsQtCommon/service/stock/svr_stock.py
dsQtCommon/service/vcoin/__init__.py
dsQtCommon/types/__init__.py
dsQtCommon/types/common/__init__.py
dsQtCommon/types/common/types.py
dsQtCommon/types/stock/__init__.py
dsQtCommon/types/stock/types.py
dsQtCommon/types/vcoin/__init__.py
dsQtCommon-0.0.4.dist-info/LICENSE
dsQtCommon-0.0.4.dist-info/METADATA
dsQtCommon-0.0.4.dist-info/WHEEL
dsQtCommon-0.0.4.dist-info/top_level.txt
dsQtCommon-0.0.4.dist-info/zip-safe
dsQtCommon-0.0.4.dist-info/RECORD
