Metadata-Version: 2.1
Name: dsQtCommon
Version: 0.0.4
Summary: DS's Quantized Transaction common library.
Home-page: https://gitee.com/dragonsun7/dsQtCommon.git
Author: Dragon Sun
Author-email: dragonsun7@163.com
License: MIT
Keywords: dsQtCommon
Platform: UNKNOWN
Classifier: Programming Language :: Python :: 3
Classifier: License :: OSI Approved :: MIT License
Classifier: Operating System :: OS Independent
Requires-Python: >=3.6
Requires-Dist: dsPyLib
